ai_homeless_man/__init__.py
ai_homeless_man-1768297.363.45.dist-info/licenses/LICENSE
ai_homeless_man-1768297.363.45.dist-info/METADATA
ai_homeless_man-1768297.363.45.dist-info/WHEEL
ai_homeless_man-1768297.363.45.dist-info/top_level.txt
ai_homeless_man-1768297.363.45.dist-info/RECORD
