Metadata-Version: 2.4
Name: ai-homeless-man
Version: 1768297.363.45
Summary: High-quality integration for https://supermaker.ai/blog/how-to-do-ai-homeless-man-to-prank-your-friends-family-tiktok-viral-tutorial/
Home-page: https://supermaker.ai/blog/how-to-do-ai-homeless-man-to-prank-your-friends-family-tiktok-viral-tutorial/
Author: SuperMaker
Classifier: Programming Language :: Python :: 3
Classifier: License :: OSI Approved :: MIT License
Requires-Python: >=3.6
License-File: LICENSE
Dynamic: author
Dynamic: classifier
Dynamic: description
Dynamic: description-content-type
Dynamic: home-page
Dynamic: license-file
Dynamic: requires-python
Dynamic: summary
